beniget
callsites-jupyternb-micro-benchmark
callsites-jupyternb-real-world-benchmark
daswow
framework_models
headergen
pycg_extended
typestub-database
