Metadata-Version: 2.2
Name: headergen
Version: 2.0.0
Summary: HeaderGen: Automated cell header generator
Home-page: https://github.com/ashwinprasadme/headergen
Author: Ashwin Prasad SV
Author-email: ashwinprasad.me@gmail.com
Requires-Dist: black
Requires-Dist: click
Requires-Dist: dill
Requires-Dist: fastapi
Requires-Dist: gast
Requires-Dist: intervaltree
Requires-Dist: isort
Requires-Dist: jedi
Requires-Dist: jupyter
Requires-Dist: jupyter_contrib_nbextensions
Requires-Dist: jupyterlab
Requires-Dist: jupytext
Requires-Dist: keras
Requires-Dist: lightgbm
Requires-Dist: nltk
Requires-Dist: numpy
Requires-Dist: pandas
Requires-Dist: plotly
Requires-Dist: pre-commit
Requires-Dist: protobuf
Requires-Dist: pygtrie
Requires-Dist: pytype
Requires-Dist: ruff
Requires-Dist: scikit-learn
Requires-Dist: scipy
Requires-Dist: seaborn
Requires-Dist: simplejson
Requires-Dist: statsmodels
Requires-Dist: tensorflow
Requires-Dist: uvicorn
Requires-Dist: xgboost
Requires-Dist: geopy
Requires-Dist: line_profiler
Requires-Dist: psycopg2-binary
Requires-Dist: redis
Requires-Dist: nibabel
Requires-Dist: aiofiles
Requires-Dist: python-multipart
Dynamic: author
Dynamic: author-email
Dynamic: description
Dynamic: description-content-type
Dynamic: home-page
Dynamic: requires-dist
Dynamic: summary
